aiogram_deta/__about__.py
aiogram_deta/__init__.py
aiogram_deta/storage.py
aiogram_deta-1.0.0a0.dist-info/METADATA
aiogram_deta-1.0.0a0.dist-info/WHEEL
aiogram_deta-1.0.0a0.dist-info/licenses/LICENSE
aiogram_deta-1.0.0a0.dist-info/RECORD
